jsify/__init__.py
jsify/assertion.py
jsify/calls.py
jsify/encoder.py
jsify/exceptions.py
jsify/jsify.py
jsify/simple.py
jsify/stringcase.py
jsify/undefined.py
tests/__init__.py
tests/tests_jsify.py
jsify-0.9.7.dist-info/LICENSE
jsify-0.9.7.dist-info/METADATA
jsify-0.9.7.dist-info/WHEEL
jsify-0.9.7.dist-info/top_level.txt
jsify-0.9.7.dist-info/RECORD
