Metadata-Version: 2.1
Name: jsify
Version: 0.9.7
Summary: Jsify is a Python library designed to bridge the gap between Python's data structures and JSON-like objects, offering seamless integration and manipulation of data in a JavaScript-like manner.With Jsify, you can effortlessly convert Python dictionaries, lists, and tuples into JSON-like objects that support attribute-style access (dot notation), automatic handling of undefined properties, and easy serialization.
Home-page: https://github.com/citsystems/jsify
Author: Zbigniew Rajewski
Author-email: zbigniew.r@citsystems.pl
Project-URL: Documentation, https://citsystems.github.io/jsify
Project-URL: Source, https://github.com/citsystems/jsify
Project-URL: Tracker, https://github.com/citsystems/jsify/issues
Keywords: json javascript objects jsify dot notation attributes serialization
Classifier: Programming Language :: Python :: 3
Classifier: License :: OSI Approved :: MIT License
Classifier: Operating System :: OS Independent
Requires-Python: >=3.0
License-File: LICENSE
Provides-Extra: dev
Requires-Dist: pytest (>=3.7) ; extra == 'dev'
Requires-Dist: sphinx (>=3.5.3) ; extra == 'dev'
